hasty/__init__.py
hasty/activity.py
hasty/attribute.py
hasty/automated_labeling.py
hasty/bucket.py
hasty/client.py
hasty/constants.py
hasty/dataset.py
hasty/exception.py
hasty/export_job.py
hasty/hasty_object.py
hasty/helper.py
hasty/image.py
hasty/label.py
hasty/label_attribute.py
hasty/label_class.py
hasty/label_utils.py
hasty/project.py
hasty/requester.py
hasty/tag.py
hasty/tag_class.py
hasty/video.py
hasty/workspace.py
hasty/inference/__init__.py
hasty/inference/attributer.py
hasty/inference/base.py
hasty/inference/detector.py
hasty/inference/instance_segmentor.py
hasty/inference/semantic_segmentor.py
hasty-0.3.12.dist-info/licenses/LICENSE
hasty-0.3.12.dist-info/METADATA
hasty-0.3.12.dist-info/WHEEL
hasty-0.3.12.dist-info/top_level.txt
hasty-0.3.12.dist-info/RECORD
